{
  "shift_index": 1862552,
  "captured_at": "2026-05-16T17:19:06.788517Z",
  "capture_file": "captures/capture_Stah1090MHZ.bin",
  "slice_start_byte": 0,
  "sample_rate_msps": 2,
  "final_decision": true,
  "c1_ratio": 19.542,
  "c2_match": true,
  "c3_power_ratio": 2.5227,
  "c4_null_count": 4,
  "snr_db": -1.94,
  "hex_message": "8FFFFEBFF7DFE7EE4FFC7BDFFFED",
  "crc_valid": false,
  "icao": "FFFEBF",
  "typecode": 30,
  "df": 17,
  "message_type": "INVALID_CRC",
  "altitude_ft": null,
  "altitude_m": null,
  "latitude": null,
  "longitude": null,
  "raw_cpr_lat": null,
  "raw_cpr_lon": null,
  "cpr_format": null,
  "callsign": null,
  "groundspeed_kt": null,
  "groundspeed_kmh": null,
  "track_angle_deg": null,
  "airspeed_kt": null,
  "airspeed_kmh": null,
  "heading_deg": null,
  "vertical_rate_fpm": null,
  "vertical_rate_ms": null,
  "vertical_status": null
}